minecraft_runner/__init__.py
minecraft_runner/config.py
minecraft_runner/exceptions.py
minecraft_runner/util.py
minecraft_runner/cli/__init__.py
minecraft_runner/cli/cli.py
minecraft_runner/cli/util.py
minecraft_runner/manage/__init__.py
minecraft_runner/manage/container.py
minecraft_runner-0.0.2.dist-info/LICENSE
minecraft_runner-0.0.2.dist-info/METADATA
minecraft_runner-0.0.2.dist-info/WHEEL
minecraft_runner-0.0.2.dist-info/entry_points.txt
minecraft_runner-0.0.2.dist-info/top_level.txt
minecraft_runner-0.0.2.dist-info/RECORD
