Metadata-Version: 2.1
Name: minecraft-runner
Version: 0.0.2
Summary: Minecraft server management made easy.
Home-page: https://git.jharmison.com/jharmison/minecraft-runner
Author: James Harmison
Author-email: jharmison@gmail.com
License: BSD-2-Clause
Platform: UNKNOWN
Requires-Python: >=3.6
Requires-Dist: click
Requires-Dist: pydantic
